setup.py
bin/ipasn-fullhistory_redis
bin/ipasn_redis
ipasn_redis/__init__.py
ipasn_redis/api.py
ipasn_redis.egg-info/PKG-INFO
ipasn_redis.egg-info/SOURCES.txt
ipasn_redis.egg-info/dependency_links.txt
ipasn_redis.egg-info/requires.txt
ipasn_redis.egg-info/top_level.txt